pysatMissions/__init__.py
pysatMissions/plot.py
pysatMissions/version.txt
pysatMissions/instruments/__init__.py
pysatMissions/instruments/_core.py
pysatMissions/instruments/pysat_ephem.py
pysatMissions/instruments/pysat_sgp4.py
pysatMissions/methods/__init__.py
pysatMissions/methods/empirical.py
pysatMissions/methods/magcoord.py
pysatMissions/methods/spacecraft.py
pysatMissions/tests/__init__.py
pysatMissions/tests/test_core.py
pysatMissions/tests/test_instruments.py
pysatMissions/tests/test_methods_empirical.py
pysatMissions/tests/test_methods_magcoord.py
pysatMissions/tests/test_methods_spacecraft.py
pysatMissions/tests/test_plot.py
pysatMissions-0.2.1.dist-info/LICENSE.md
pysatMissions-0.2.1.dist-info/METADATA
pysatMissions-0.2.1.dist-info/WHEEL
pysatMissions-0.2.1.dist-info/top_level.txt
pysatMissions-0.2.1.dist-info/RECORD
